PRED_search.py
__init__.py
PRED_search-0.2.2.dist-info/LICENSE
PRED_search-0.2.2.dist-info/METADATA
PRED_search-0.2.2.dist-info/WHEEL
PRED_search-0.2.2.dist-info/top_level.txt
PRED_search-0.2.2.dist-info/RECORD
