Metadata-Version: 2.1
Name: PRED-search
Version: 0.2.2
Summary: Search predatory journals based on the Norwegian Register for Scientific Journals, Series and Publishers
Author-email: PeTPPPP <ceklaszorp@freemail.hu>
Classifier: Programming Language :: Python :: 3
Classifier: License :: OSI Approved :: MIT License
Classifier: Operating System :: OS Independent
Requires-Python: >=3.8
License-File: LICENSE
Requires-Dist: lxml
